tictronome/__init__.py
tictronome/tictronome.py
tictronome/colors/__init__.py
tictronome/colors/ansi.py
tictronome/colors/colored_string.py
tictronome-0.1.1.dist-info/LICENSE
tictronome-0.1.1.dist-info/METADATA
tictronome-0.1.1.dist-info/WHEEL
tictronome-0.1.1.dist-info/top_level.txt
tictronome-0.1.1.dist-info/RECORD
