Metadata-Version: 2.1
Name: tictronome
Version: 0.1.1
Summary: A simple python CLI that can relieve stress while running long scripts.
Home-page: https://github.com/donny-son/tictronome
Author: Dongook Son
Author-email: dongook.son@yonsei.ac.kr
License: UNKNOWN
Project-URL: Bug Tracker, https://github.com/donny-son/tictronome/issue
Platform: UNKNOWN
Classifier: Programming Language :: Python :: 3
Classifier: License :: OSI Approved :: MIT License
Classifier: Operating System :: OS Independent
Requires-Python: >=3.6
